LICENSE
MANIFEST.in
README.rst
setup.py
bin/add_blast_results_to_gff3_product.py
bin/add_gff3_locus_tags.py
bin/add_polypeptide_to_gff3_gene_models.py
bin/append_to_column_9_value.py
bin/append_to_fasta_header.py
bin/append_to_fastq_read_header.py
bin/calculate_gene_coverage_from_assembly.py
bin/calculate_query_coverage_by_blast.py
bin/check_for_embedded_fasta_headers.py
bin/check_gff_for_internal_stops.py
bin/compare_gene_structures.py
bin/convert_aat_btab_to_gff3.py
bin/convert_augustus_to_gff3.py
bin/convert_blast_btab_to_bed.py
bin/convert_blast_btab_to_gff3.py
bin/convert_cegma_gff_to_gff3.py
bin/convert_cufflinks_gtf_to_gff3.py
bin/convert_fasta_contigs_to_gff3.py
bin/convert_fastq_to_fasta.py
bin/convert_genbank_to_gff3.py
bin/convert_gff3_to_bed.py
bin/convert_gff3_to_gbk.py
bin/convert_gff3_to_gene_association_format.py
bin/convert_gff3_to_ncbi_tbl.py
bin/convert_gff_to_ncbi_gff3.py
bin/convert_glimmerHMM_gff_to_gff3.py
bin/convert_htab_to_bed.py
bin/convert_metagenemark_gff_to_gff3.py
bin/convert_pasa_gff_to_models.py
bin/convert_prodigal_to_gff3.py
bin/convert_scipio_gff_to_gff3.py
bin/convert_stringtie_gtf_to_gff3.py
bin/correct_gff3_CDS_phase_column.py
bin/create_rsem_html_table.py
bin/create_taxonomic_profile_from_blast.py
bin/create_taxonomy_db.py
bin/detect_inverted_repeats.py
bin/download_assemblies_from_genbank.py
bin/eggnog_to_sqlite3.py
bin/export_fasta_ids.py
bin/extend_genes_to_stops.py
bin/extract_fasta_regions.py
bin/fasta_base_content.py
bin/fasta_simple_stats.py
bin/fasta_size_distribution_plot.py
bin/fasta_size_report.py
bin/fastq_simple_stats.py
bin/filter_fasta_by_abundance.py
bin/filter_fasta_by_header_regex.py
bin/filter_fasta_by_type.py
bin/filter_fastq_by_N_content.py
bin/filter_gff3_by_id_list.py
bin/filter_uniref_by_repid.py
bin/filter_uniref_by_taxonomy.py
bin/get_mpilup_from_id_list.py
bin/hmmlib_to_sqlite3.py
bin/interleave_fasta.py
bin/interleave_fastq.py
bin/join_columnar_files.py
bin/list_biocode.py
biocode.egg-info/PKG-INFO
biocode.egg-info/SOURCES.txt
biocode.egg-info/dependency_links.txt
biocode.egg-info/not-zip-safe
biocode.egg-info/requires.txt
biocode.egg-info/top_level.txt
