Metadata-Version: 2.1
Name: biocode
Version: 0.12.0
Summary: Bioinformatics code libraries and scripts
Home-page: http://github.com/jorvis/biocode
Author: Joshua Orvis
Author-email: jorvis@gmail.com
License: MIT
Keywords: bioinformatics scripts modules gff3 fasta fastq bam sam
Platform: UNKNOWN
Classifier: Development Status :: 5 - Production/Stable
Classifier: Environment :: Console
Classifier: Intended Audience :: Science/Research
Classifier: License :: OSI Approved :: MIT License
Classifier: Natural Language :: English
Classifier: Programming Language :: Python :: 3
Classifier: Topic :: Scientific/Engineering :: Bio-Informatics
License-File: LICENSE
